Metadata-Version: 2.1
Name: mpl-tc-fonts
Version: 1.0.1
Summary: 🇹🇼 A package to solve the problem of "Tofu" in your matplotlib plots whenever you're trying to use Traditional Chinese characters in labels or texts.
Home-page: https://github.com/Hsins/mpl-tc-fonts
Author: Hsins
Author-email: hsinspeng@gmail.com
License: UNKNOWN
Project-URL: Bug Reports, https://github.com/Hsins/mpl-tc-fonts/issues
Project-URL: Funding, https://donate.pypi.org
Project-URL: Say Thanks!, http://saythanks.io/to/example
Project-URL: Source, https://github.com/Hsins/mpl-tc-fonts
Keywords: sample,setuptools,development
Platform: UNKNOWN
Classifier: Development Status :: 3 - Alpha
Classifier: Intended Audience :: Developers
Classifier: Topic :: Software Development :: Build Tools
Classifier: License :: OSI Approved :: MIT License
Classifier: Programming Language :: Python :: 3
Classifier: Programming Language :: Python :: 3.5
Classifier: Programming Language :: Python :: 3.6
Classifier: Programming Language :: Python :: 3.7
Classifier: Programming Language :: Python :: 3.8
Classifier: Programming Language :: Python :: 3 :: Only
Requires-Python: >=3.5, <4
Provides-Extra: dev
Provides-Extra: test
